fastlingo/__init__.py
fastlingo/main.py
fastlingo/core/__init__.py
fastlingo/core/cache.py
fastlingo/core/cache_lru.py
fastlingo/core/config.py
fastlingo/core/double_linked_list.py
fastlingo/core/exceptions.py
fastlingo/core/field.py
fastlingo/core/fileio.py
fastlingo/core/language.py
fastlingo/core/language_utils.py
fastlingo/core/logger.py
fastlingo/core/translations_cache.py
fastlingo/core/translator.py
fastlingo/core/utils.py
fastlingo/translate_services/__init__.py
fastlingo/translate_services/translate.py
fastlingo/translate_services/translate_factory.py
fastlingo/translate_services/translate_google.py
fastlingo/translate_services/translate_service.py
fastlingo-1.2.0.dist-info/METADATA
fastlingo-1.2.0.dist-info/WHEEL
fastlingo-1.2.0.dist-info/entry_points.txt
fastlingo-1.2.0.dist-info/top_level.txt
fastlingo-1.2.0.dist-info/RECORD
