Metadata-Version: 2.1
Name: fastlingo
Version: 1.2.0
Summary: FastLingo is a command-line tool designed to translate and manage app metadata within Fastlane projects.
Author-email: Fırat Tamur <ftamur16@ku.edu.tr>
Project-URL: homepage, https://github.com/firattamur/fastlingo
Project-URL: repository, https://github.com/firattamur/fastlingo
Project-URL: documentation, https://github.com/firattamur/fastlingo
Keywords: fastlane,localization,translation,localize,translate,localization-management
Classifier: Development Status :: 4 - Beta
Classifier: License :: OSI Approved :: MIT License
Classifier: Environment :: Console
Classifier: Intended Audience :: Developers
Classifier: Intended Audience :: Information Technology
Classifier: Programming Language :: Python :: 3.7
Classifier: Programming Language :: Python :: 3.8
Classifier: Programming Language :: Python :: 3.9
Classifier: Programming Language :: Python :: 3.10
Classifier: Operating System :: OS Independent
Classifier: Topic :: Software Development :: Localization
Classifier: Topic :: Software Development :: Libraries :: Python Modules
Classifier: Topic :: Text Processing :: Linguistic
Requires-Python: >=3.7
Requires-Dist: click
Requires-Dist: google-cloud-translate
Requires-Dist: toml
Provides-Extra: dev
Requires-Dist: pytest ; extra == 'dev'
Requires-Dist: mypy ; extra == 'dev'
Requires-Dist: ruff ; extra == 'dev'
Requires-Dist: black ; extra == 'dev'
Requires-Dist: isort ; extra == 'dev'
Requires-Dist: sphinx ; extra == 'dev'
Requires-Dist: furo ; extra == 'dev'
Requires-Dist: pip-tools ; extra == 'dev'
